{
  "problems": [
    {
      "problemId": 5582,
      "title": "공통 부분 문자열",
      "tier": "💛 Gold 5",
      "selectedAt": "2025-12-17T14:00:00.000Z",
      "url": "https://www.acmicpc.net/problem/5582"
    },
    {
      "problemId": 2011,
      "title": "암호코드",
      "tier": "💛 Gold 5",
      "selectedAt": "2025-12-18T14:01:00.000Z",
      "url": "https://www.acmicpc.net/problem/2011"
    },
    {
      "problemId": 10159,
      "title": "저울",
      "tier": "💛 Gold 4",
      "selectedAt": "2025-12-22T14:02:00.000Z",
      "url": "https://www.acmicpc.net/problem/10159"
    },
    {
      "problemId": 10282,
      "title": "해킹",
      "tier": "💛 Gold 4",
      "selectedAt": "2025-12-23T14:03:00.000Z",
      "url": "https://www.acmicpc.net/problem/10282"
    },
    {
      "problemId": 1911,
      "title": "흙길 보수하기",
      "tier": "💛 Gold 5",
      "selectedAt": "2025-12-24T14:04:00.000Z",
      "url": "https://www.acmicpc.net/problem/1911"
    },
    {
      "problemId": 6198,
      "title": "옥상 정원 꾸미기",
      "tier": "💛 Gold 5",
      "selectedAt": "2025-12-26T14:05:00.000Z",
      "url": "https://www.acmicpc.net/problem/6198"
    },
    {
      "problemId": 17406,
      "title": "배열 돌리기 4",
      "tier": "💛 Gold 4",
      "selectedAt": "2025-12-29T14:06:00.000Z",
      "url": "https://www.acmicpc.net/problem/17406"
    },
    {
      "problemId": 15989,
      "title": "1, 2, 3 더하기 4",
      "tier": "💛 Gold 5",
      "selectedAt": "2025-12-30T14:07:00.000Z",
      "url": "https://www.acmicpc.net/problem/15989"
    },
    {
      "problemId": 5972,
      "title": "택배 배송",
      "tier": "💛 Gold 5",
      "selectedAt": "2025-12-30T14:08:00.000Z",
      "url": "https://www.acmicpc.net/problem/5972"
    },
    {
      "problemId": 2981,
      "title": "검문",
      "tier": "💛 Gold 4",
      "selectedAt": "2026-01-01T14:09:00.000Z",
      "url": "https://www.acmicpc.net/problem/2981"
    },
    {
      "problemId": 5557,
      "title": "1학년",
      "tier": "💛 Gold 5",
      "selectedAt": "2026-01-01T14:10:00.000Z",
      "url": "https://www.acmicpc.net/problem/5557"
    },
    {
      "problemId": 4803,
      "title": "트리",
      "tier": "💛 Gold 4",
      "selectedAt": "2026-01-03T14:11:00.000Z",
      "url": "https://www.acmicpc.net/problem/4803"
    },
    {
      "problemId": 2589,
      "title": "보물섬",
      "tier": "💛 Gold 5",
      "selectedAt": "2026-01-04T14:12:00.000Z",
      "url": "https://www.acmicpc.net/problem/2589"
    },
    {
      "problemId": 1240,
      "title": "노드사이의 거리",
      "tier": "💛 Gold 5",
      "selectedAt": "2026-01-06T14:13:00.000Z",
      "url": "https://www.acmicpc.net/problem/1240"
    },
    {
      "problemId": 1461,
      "title": "도서관",
      "tier": "💛 Gold 4",
      "selectedAt": "2026-01-07T14:14:00.000Z",
      "url": "https://www.acmicpc.net/problem/1461"
    },
    {
      "problemId": 17281,
      "title": "⚾",
      "tier": "💛 Gold 4",
      "selectedAt": "2026-01-08T14:15:00.000Z",
      "url": "https://www.acmicpc.net/problem/17281"
    },
    {
      "problemId": 16935,
      "title": "배열 돌리기 3",
      "tier": "💛 Gold 5",
      "selectedAt": "2026-01-09T14:16:00.000Z",
      "url": "https://www.acmicpc.net/problem/16935"
    },
    {
      "problemId": 1915,
      "title": "가장 큰 정사각형",
      "tier": "💛 Gold 4",
      "selectedAt": "2026-01-09T14:17:00.000Z",
      "url": "https://www.acmicpc.net/problem/1915"
    },
    {
      "problemId": 2448,
      "title": "별 찍기 - 11",
      "tier": "💛 Gold 4",
      "selectedAt": "2026-01-12T14:18:00.000Z",
      "url": "https://www.acmicpc.net/problem/2448"
    },
    {
      "problemId": 13975,
      "title": "파일 합치기 3",
      "tier": "💛 Gold 4",
      "selectedAt": "2026-01-12T14:19:00.000Z",
      "url": "https://www.acmicpc.net/problem/13975"
    },
    {
      "problemId": 2302,
      "title": "극장 좌석",
      "tier": "💛 Gold 5",
      "selectedAt": "2026-01-13T14:20:00.000Z",
      "url": "https://www.acmicpc.net/problem/2302"
    },
    {
      "problemId": 3079,
      "title": "입국심사",
      "tier": "💛 Gold 5",
      "selectedAt": "2026-01-13T14:21:00.000Z",
      "url": "https://www.acmicpc.net/problem/3079"
    },
    {
      "problemId": 2170,
      "title": "선 긋기",
      "tier": "💛 Gold 5",
      "selectedAt": "2026-01-14T14:22:00.000Z",
      "url": "https://www.acmicpc.net/problem/2170"
    },
    {
      "problemId": 1963,
      "title": "소수 경로",
      "tier": "💛 Gold 4",
      "selectedAt": "2026-01-15T14:23:00.000Z",
      "url": "https://www.acmicpc.net/problem/1963"
    },
    {
      "problemId": 1038,
      "title": "감소하는 수",
      "tier": "💛 Gold 5",
      "selectedAt": "2026-01-16T14:24:00.000Z",
      "url": "https://www.acmicpc.net/problem/1038"
    },
    {
      "problemId": 2023,
      "title": "신기한 소수",
      "tier": "💛 Gold 5",
      "selectedAt": "2026-01-19T14:25:00.000Z",
      "url": "https://www.acmicpc.net/problem/2023"
    },
    {
      "problemId": 4179,
      "title": "불",
      "tier": "💛 Gold 4",
      "selectedAt": "2026-01-20T14:26:00.000Z",
      "url": "https://www.acmicpc.net/problem/4179"
    },
    {
      "problemId": 4811,
      "title": "알약",
      "tier": "💛 Gold 5",
      "selectedAt": "2026-01-21T14:27:00.000Z",
      "url": "https://www.acmicpc.net/problem/4811"
    },
    {
      "problemId": 7490,
      "title": "0 만들기",
      "tier": "💛 Gold 5",
      "selectedAt": "2026-01-22T14:28:00.000Z",
      "url": "https://www.acmicpc.net/problem/7490"
    },
    {
      "problemId": 2234,
      "title": "성곽",
      "tier": "💛 Gold 3",
      "selectedAt": "2026-01-27T14:29:00.000Z",
      "url": "https://www.acmicpc.net/problem/2234"
    },
    {
      "problemId": 2615,
      "title": "오목",
      "tier": "💛 Gold 5",
      "selectedAt": "2026-01-27T14:30:00.000Z",
      "url": "https://www.acmicpc.net/problem/2615"
    },
    {
      "problemId": 15961,
      "title": "회전 초밥",
      "tier": "💛 Gold 4",
      "selectedAt": "2026-01-28T14:31:00.000Z",
      "url": "https://www.acmicpc.net/problem/15961"
    },
    {
      "problemId": 1914,
      "title": "하노이 탑",
      "tier": "💛 Gold 5",
      "selectedAt": "2026-01-29T14:32:00.000Z",
      "url": "https://www.acmicpc.net/problem/1914"
    },
    {
      "problemId": 11559,
      "title": "Puyo Puyo",
      "tier": "💛 Gold 4",
      "selectedAt": "2026-02-02T14:33:00.000Z",
      "url": "https://www.acmicpc.net/problem/11559"
    },
    {
      "problemId": 2749,
      "title": "피보나치 수 3",
      "tier": "💛 Gold 2",
      "selectedAt": "2026-02-03T14:34:00.000Z",
      "url": "https://www.acmicpc.net/problem/2749"
    },
    {
      "problemId": 2230,
      "title": "수 고르기",
      "tier": "💛 Gold 5",
      "selectedAt": "2026-02-03T14:35:00.000Z",
      "url": "https://www.acmicpc.net/problem/2230"
    },
    {
      "problemId": 18405,
      "title": "경쟁적 전염",
      "tier": "💛 Gold 5",
      "selectedAt": "2026-02-04T14:36:00.000Z",
      "url": "https://www.acmicpc.net/problem/18405"
    },
    {
      "problemId": 10986,
      "title": "나머지 합",
      "tier": "💛 Gold 3",
      "selectedAt": "2026-02-04T14:37:00.000Z",
      "url": "https://www.acmicpc.net/problem/10986"
    },
    {
      "problemId": 1958,
      "title": "LCS 3",
      "tier": "💛 Gold 4",
      "selectedAt": "2026-02-05T14:38:00.000Z",
      "url": "https://www.acmicpc.net/problem/1958"
    },
    {
      "problemId": 1351,
      "title": "무한 수열",
      "tier": "💛 Gold 5",
      "selectedAt": "2026-02-09T14:39:00.000Z",
      "url": "https://www.acmicpc.net/problem/1351"
    },
    {
      "problemId": 2056,
      "title": "작업",
      "tier": "💛 Gold 4",
      "selectedAt": "2026-02-10T14:40:00.000Z",
      "url": "https://www.acmicpc.net/problem/2056"
    },
    {
      "problemId": 1074,
      "title": "Z",
      "tier": "💛 Gold 5",
      "selectedAt": "2026-02-19T14:41:00.000Z",
      "url": "https://www.acmicpc.net/problem/1074"
    },
    {
      "problemId": 2636,
      "title": "치즈",
      "tier": "💛 Gold 4",
      "selectedAt": "2026-02-23T14:42:00.000Z",
      "url": "https://www.acmicpc.net/problem/2636"
    },
    {
      "problemId": 1256,
      "title": "사전",
      "tier": "💛 Gold 2",
      "selectedAt": "2026-02-24T14:43:00.000Z",
      "url": "https://www.acmicpc.net/problem/1256"
    },
    {
      "problemId": 16926,
      "title": "배열 돌리기 1",
      "tier": "💛 Gold 5",
      "selectedAt": "2026-03-03T14:44:00.000Z",
      "url": "https://www.acmicpc.net/problem/16926"
    }
  ]
}
